wasabicli/__init__.py
wasabicli/cli.py
wasabicli/wasabicli.py
wasabicli/utils/__init__.py
wasabicli/utils/formatter.py
wasabicli-4.0.0.dist-info/AUTHORS.rst
wasabicli-4.0.0.dist-info/LICENSE
wasabicli-4.0.0.dist-info/METADATA
wasabicli-4.0.0.dist-info/WHEEL
wasabicli-4.0.0.dist-info/entry_points.txt
wasabicli-4.0.0.dist-info/top_level.txt
wasabicli-4.0.0.dist-info/RECORD
