Metadata-Version: 2.1
Name: wasabicli
Version: 4.0.0
Summary: CLI application for management of versioned Wasabi S3 buckets
Home-page: https://github.com/salimdason/wasabicli
Author: Mohammed Salim Dason
Author-email: salimdason@outlook.com
License: GNU General Public License v3
Keywords: wasabicli
Classifier: Development Status :: 2 - Pre-Alpha
Classifier: Intended Audience :: Developers
Classifier: License :: OSI Approved :: GNU General Public License v3 (GPLv3)
Classifier: Natural Language :: English
Classifier: Programming Language :: Python :: 3
Classifier: Programming Language :: Python :: 3.6
Classifier: Programming Language :: Python :: 3.7
Classifier: Programming Language :: Python :: 3.8
Requires-Python: >=3.6
License-File: LICENSE
License-File: AUTHORS.rst
Requires-Dist: Click (>=7.0)
